distinanet/__init__.py
distinanet/cli.py
distinanet/config.py
distinanet/backbones/__init__.py
distinanet/backbones/fpn.py
distinanet/backbones/resnet.py
distinanet/core/anchors.py
distinanet/core/blocks.py
distinanet/core/box_ops.py
distinanet/core/losses.py
distinanet/engine/checkpoint_manager.py
distinanet/engine/dataloader_setup.py
distinanet/engine/logging.py
distinanet/engine/optim.py
distinanet/engine/trainer.py
distinanet/evaluation/evaluator.py
distinanet/evaluation/inference_engine.py
distinanet/evaluation/metrics.py
distinanet/evaluation/results_handler.py
distinanet/heads/__init__.py
distinanet/heads/classification_head.py
distinanet/heads/distance_heads.py
distinanet/heads/regression_head.py
distinanet/model/__init__.py
distinanet/model/model.py
distinanet/scripts/__init__.py
distinanet/scripts/inference.py
distinanet/scripts/test.py
distinanet/scripts/train.py
distinanet/scripts/video.py
distinanet/utils/__init__.py
distinanet/utils/common.py
distinanet/utils/evaluator.py
distinanet/utils/logging_utils.py
distinanet/utils/trainer.py
distinanet-1.0.1.dist-info/METADATA
distinanet-1.0.1.dist-info/WHEEL
distinanet-1.0.1.dist-info/entry_points.txt
distinanet-1.0.1.dist-info/licenses/LICENSE
distinanet-1.0.1.dist-info/RECORD
