Metadata-Version: 2.4
Name: distinanet
Version: 1.0.1
Summary: DistinaNet: RetinaNet with Distance Estimation for simultaneous object detection and distance estimation
Project-URL: Homepage, https://github.com/jonher16/distinanet
Project-URL: Repository, https://github.com/jonher16/distinanet
Project-URL: Documentation, https://distinanet.readthedocs.io
Project-URL: Bug Reports, https://github.com/jonher16/distinanet/issues
Author-email: Jon Hernandez Aranda <jonher16@kaist.ac.kr>
License-Expression: Apache-2.0
License-File: LICENSE
Keywords: computer vision,deep learning,distance estimation,object detection,pytorch,retinanet
Classifier: Development Status :: 4 - Beta
Classifier: Intended Audience :: Developers
Classifier: Intended Audience :: Science/Research
Classifier: Operating System :: OS Independent
Classifier: Programming Language :: Python :: 3
Classifier: Programming Language :: Python :: 3.9
Classifier: Programming Language :: Python :: 3.10
Classifier: Programming Language :: Python :: 3.11
Classifier: Topic :: Scientific/Engineering :: Artificial Intelligence
Requires-Python: >=3.9
Requires-Dist: matplotlib>=3.5.0
Requires-Dist: numpy<2.0.0,>=1.20.0
Requires-Dist: opencv-python<4.10.0,>=4.5.0
Requires-Dist: pandas>=1.5.0
Requires-Dist: pillow>=8.0.0
Requires-Dist: scikit-image>=0.19.0
Requires-Dist: scikit-learn>=1.0.0
Requires-Dist: six>=1.16.0
Requires-Dist: tensorboard>=2.8.0
Requires-Dist: torch>=1.13.0
Requires-Dist: torchvision>=0.14.0
Requires-Dist: tqdm>=4.60.0
